autopyre.py
autopyre-1.0.3.dist-info/LICENSE
autopyre-1.0.3.dist-info/METADATA
autopyre-1.0.3.dist-info/WHEEL
autopyre-1.0.3.dist-info/entry_points.txt
autopyre-1.0.3.dist-info/top_level.txt
autopyre-1.0.3.dist-info/RECORD
